tomcli/__init__.py
tomcli/__main__.py
tomcli/_peekable.py
tomcli/py.typed
tomcli/toml.py
tomcli/cli/__init__.py
tomcli/cli/_util.py
tomcli/cli/formatters.py
tomcli/cli/get.py
tomcli/cli/main.py
tomcli/cli/set.py
tomcli/formatters/__init__.py
tomcli/formatters/builtin.py
tomcli-0.10.1.dist-info/entry_points.txt
tomcli-0.10.1.dist-info/licenses/LICENSE
tomcli-0.10.1.dist-info/WHEEL
tomcli-0.10.1.dist-info/METADATA
tomcli-0.10.1.dist-info/RECORD
