Metadata-Version: 2.4
Name: tomcli
Version: 0.10.1
Summary: CLI for working with TOML files. Pronounced "tom clee."
Author-email: Maxwell G <maxwell@gtmx.me>
Requires-Python: >=3.9
Classifier: Development Status :: 3 - Alpha
Classifier: Environment :: Console
Classifier: Programming Language :: Python
Classifier: Programming Language :: Python :: 3.9
Classifier: Programming Language :: Python :: 3.10
Classifier: Programming Language :: Python :: 3.11
Classifier: Programming Language :: Python :: 3.12
Classifier: Programming Language :: Python :: 3.13
Classifier: Programming Language :: Python :: 3.14
Classifier: Typing :: Typed
License-File: LICENSE
Requires-Dist: click
Requires-Dist: importlib_metadata; python_version<'3.11'
Requires-Dist: tomlkit ; extra == "all"
Requires-Dist: ruff >= 0.3.0 ; extra == "codeqa"
Requires-Dist: reuse ; extra == "codeqa"
Requires-Dist: tomcli[all] ; extra == "dev"
Requires-Dist: tomcli[codeqa] ; extra == "dev"
Requires-Dist: tomcli[formatters] ; extra == "dev"
Requires-Dist: tomcli[test] ; extra == "dev"
Requires-Dist: tomcli[typing] ; extra == "dev"
Requires-Dist: nox ; extra == "dev"
Requires-Dist: black>=24 ; extra == "formatters"
Requires-Dist: isort ; extra == "formatters"
Requires-Dist: pytest ; extra == "test"
Requires-Dist: tomli  ; extra == "tomli" and ( python_version<'3.11')
Requires-Dist: tomli_w ; extra == "tomli"
Requires-Dist: tomlkit ; extra == "tomlkit"
Requires-Dist: basedpyright ; extra == "typing"
Requires-Dist: tomcli[tomli] ; extra == "typing"
Requires-Dist: tomcli[tomlkit] ; extra == "typing"
Requires-Dist: mkdocs-gen-files ; extra == "typing"
Requires-Dist: mypy ; extra == "typing"
Requires-Dist: pytest ; extra == "typing"
Requires-Dist: tomli ; extra == "typing"
Requires-Dist: typing_extensions ; extra == "typing"
Requires-Dist: nox ; extra == "typing"
Requires-Dist: releaserr ; extra == "typing"
Project-URL: Changelog, https://tomcli.gtmx.me/news/
Project-URL: Documentation, https://tomcli.gtmx.me
Project-URL: Homepage, https://tomcli.gtmx.me
Project-URL: Mailing List, https://lists.sr.ht/~gotmax23/tomcli
Project-URL: Source, https://git.sr.ht/~gotmax23/tomcli
Provides-Extra: all
Provides-Extra: codeqa
Provides-Extra: dev
Provides-Extra: formatters
Provides-Extra: test
Provides-Extra: tomli
Provides-Extra: tomlkit
Provides-Extra: typing
